easy_flask/__init__.py
easy_flask/app.py
easy_flask/control.sh
easy_flask/start.py
easy_flask/api/__init__.py
easy_flask/api/demo/__init__.py
easy_flask/api/demo/demo_api.py
easy_flask/conf/__init__.py
easy_flask/conf/config.ini
easy_flask/internal/__init__.py
easy_flask/internal/error.py
easy_flask/utils/__init__.py
easy_flask/utils/parser.py
easy_flask_restful-1.1.5.data/data/README.md
easy_flask_restful-1.1.5.dist-info/LICENSE
easy_flask_restful-1.1.5.dist-info/METADATA
easy_flask_restful-1.1.5.dist-info/WHEEL
easy_flask_restful-1.1.5.dist-info/entry_points.txt
easy_flask_restful-1.1.5.dist-info/top_level.txt
easy_flask_restful-1.1.5.dist-info/RECORD
