Metadata-Version: 2.1
Name: easy-flask-restful
Version: 1.1.5
Summary: Easy to Make Flask Server
Home-page: https://github.com/GuoTengda1993/easy-flask
Author: Guo Tengda
Author-email: ttguotengda@foxmail.com
License: MIT
Platform: UNKNOWN
Classifier: License :: OSI Approved :: MIT License
Classifier: Operating System :: OS Independent
Classifier: Programming Language :: Python :: 3
Classifier: Intended Audience :: Developers
Classifier: Intended Audience :: System Administrators
License-File: LICENSE
Requires-Dist: Flask (>=2.0.0)
